pdfbaker/__init__.py
pdfbaker/__main__.py
pdfbaker/baker.py
pdfbaker/console.py
pdfbaker/document.py
pdfbaker/errors.py
pdfbaker/logging.py
pdfbaker/page.py
pdfbaker/pdf.py
pdfbaker/processing.py
pdfbaker/render.py
pdfbaker/config/__init__.py
pdfbaker/config/baker.py
pdfbaker/config/document.py
pdfbaker/config/page.py
pdfbaker-0.11.3.dist-info/METADATA
pdfbaker-0.11.3.dist-info/WHEEL
pdfbaker-0.11.3.dist-info/entry_points.txt
pdfbaker-0.11.3.dist-info/licenses/LICENSE
pdfbaker-0.11.3.dist-info/RECORD
