Metadata-Version: 2.4
Name: pdfbaker
Version: 0.11.3
Summary: SVG Jinja templates + YAML config = PDF documents
Author-email: "Danny W. Adair" <danny.adair@unfold.nz>
License-File: LICENSE
Requires-Python: >=3.11
Requires-Dist: cairosvg
Requires-Dist: jinja2
Requires-Dist: pydantic
Requires-Dist: pypdf
Requires-Dist: rich-click
Requires-Dist: ruamel-yaml
